sida/__init__.py
sida/cs228/__init__.py
sida/cs228/show.py
sida/cs228/standardize.py
sida_cs228-0.0.3.dist-info/LICENSE
sida_cs228-0.0.3.dist-info/METADATA
sida_cs228-0.0.3.dist-info/WHEEL
sida_cs228-0.0.3.dist-info/top_level.txt
sida_cs228-0.0.3.dist-info/RECORD
