Metadata-Version: 2.1
Name: sida-cs228
Version: 0.0.3
Summary: UNKNOWN
Home-page: https://github.com/liusida/sida-cs228/
Author: Sida Liu
Author-email: sliu1@uvm.edu
License: UNKNOWN
Platform: UNKNOWN
Classifier: Programming Language :: Python
Classifier: License :: OSI Approved :: MIT License
Classifier: Operating System :: OS Independent
Requires-Dist: numpy
Requires-Dist: matplotlib
